Metadata-Version: 2.1
Name: approxinterpol
Version: 0.0.3
Summary: Ready-made Approximation and interpolation
Home-page: https://github.com/SMALA-comand/Approx_Interpolation
Author: Mark Kozlov
Author-email: mark.k.2012@yandex.ru
License: UNKNOWN
Platform: UNKNOWN
Classifier: Programming Language :: Python :: 3.9
Classifier: License :: OSI Approved :: MIT License
Classifier: Operating System :: OS Independent
